vasetviens/__init__.py
vasetviens/cli.py
vasetviens/core.py
vasetviens-0.1.1.dist-info/METADATA
vasetviens-0.1.1.dist-info/WHEEL
vasetviens-0.1.1.dist-info/entry_points.txt
vasetviens-0.1.1.dist-info/top_level.txt
vasetviens-0.1.1.dist-info/RECORD
