Metadata-Version: 2.4
Name: vasetviens
Version: 0.1.1
Summary: Détection automatique de va-et-vient dans des vidéos de football
License: MIT
Requires-Python: >=3.8
Requires-Dist: opencv-python
Requires-Dist: numpy
Requires-Dist: ultralytics
